pydevops/__init__.py
pydevops/__main__.py
pydevops/base.py
pydevops/cmake.py
pydevops/conan.py
pydevops/docker.py
pydevops/github.py
pydevops/sh.py
pydevops/ssh.py
pydevops/us4us.py
pydevops/utils.py
pydevops/version.py
pydevops_us4us-0.3.0.dist-info/METADATA
pydevops_us4us-0.3.0.dist-info/WHEEL
pydevops_us4us-0.3.0.dist-info/entry_points.txt
pydevops_us4us-0.3.0.dist-info/top_level.txt
pydevops_us4us-0.3.0.dist-info/RECORD
