Metadata-Version: 2.1
Name: pydevops-us4us
Version: 0.3.0
Summary: Python tools for us4us devops
Home-page: https://us4us.eu
Author: us4us Ltd.
Author-email: support@us4us.eu
License: UNKNOWN
Platform: UNKNOWN
Classifier: Development Status :: 1 - Planning
Classifier: Intended Audience :: Developers
Classifier: Programming Language :: Python :: 3
Classifier: Operating System :: OS Independent
Requires-Dist: idna
Requires-Dist: requests
